py_securestring-0.3.dist-info/DESCRIPTION.rst
py_securestring-0.3.dist-info/METADATA
py_securestring-0.3.dist-info/RECORD
py_securestring-0.3.dist-info/WHEEL
py_securestring-0.3.dist-info/metadata.json
py_securestring-0.3.dist-info/top_level.txt
securestring/__init__.py
securestring/__main__.py
securestring/securestring.py
