Metadata-Version: 2.0
Name: py-securestring
Version: 0.3
Summary: SecureString wrapper written by Python.
Home-page: https://github.com/er28-0652/securestring
Author: er28-0652
Author-email: UNKNOWN
License: MIT
Keywords: SecureString
Platform: UNKNOWN
